<?xml version="1.0" encoding="UTF-8"?><record_update sys_domain="global" table="sys_complex_object">
    <sys_complex_object action="DELETE">
        <label/>
        <name>FD0a462ebef803051048b6688991a478b8</name>
        <namespace>FlowDesigner</namespace>
        <scope_name>8518bb0a2f110110d2dbb6a62799b6aa</scope_name>
        <serialized_content>{"FlowDesigner:FD0a462ebef803051048b6688991a478b8":{"watch_name":"String","watch_name.$field_facets":{"SimpleMapFacet":"{\"uiTypeLabel\":\"String\",\"read_only\":\"false\",\"hint\":\"\",\"uiType\":\"string\",\"default_value\":\"\",\"label\":\"watch_name\",\"mandatory\":\"false\",\"order\":\"1\",\"max_length\":\"0\"}"},"policy_name":"String","policy_name.$field_facets":{"SimpleMapFacet":"{\"uiTypeLabel\":\"String\",\"read_only\":\"false\",\"hint\":\"\",\"uiType\":\"string\",\"default_value\":\"\",\"label\":\"policy_name\",\"mandatory\":\"false\",\"order\":\"2\",\"max_length\":\"0\"}"},"issues":[{"$60_issues":{"severity":"String","severity.$field_facets":{"SimpleMapFacet":"{\"uiTypeLabel\":\"String\",\"read_only\":\"false\",\"hint\":\"\",\"uiType\":\"string\",\"default_value\":\"\",\"label\":\"severity\",\"mandatory\":\"false\",\"order\":\"1\",\"max_length\":\"0\"}"},"summary":"String","summary.$field_facets":{"SimpleMapFacet":"{\"uiTypeLabel\":\"String\",\"read_only\":\"false\",\"hint\":\"\",\"uiType\":\"string\",\"default_value\":\"\",\"label\":\"summary\",\"mandatory\":\"false\",\"order\":\"5\",\"max_length\":\"0\"}"},"cve":"String","cve.$field_facets":{"SimpleMapFacet":"{\"uiTypeLabel\":\"String\",\"read_only\":\"false\",\"hint\":\"\",\"uiType\":\"string\",\"default_value\":\"\",\"label\":\"cve\",\"mandatory\":\"false\",\"order\":\"2\",\"max_length\":\"0\"}"},"created":"String","created.$field_facets":{"SimpleMapFacet":"{\"uiTypeLabel\":\"String\",\"read_only\":\"false\",\"hint\":\"\",\"uiType\":\"string\",\"default_value\":\"\",\"label\":\"created\",\"mandatory\":\"false\",\"order\":\"4\",\"max_length\":\"0\"}"},"type":"String","type.$field_facets":{"SimpleMapFacet":"{\"uiTypeLabel\":\"String\",\"read_only\":\"false\",\"hint\":\"\",\"uiType\":\"string\",\"default_value\":\"\",\"label\":\"type\",\"mandatory\":\"false\",\"order\":\"3\",\"max_length\":\"0\"}"}}}],"issues.$field_facets":{"SimpleMapFacet":"{\"max_rows\":null,\"default_value\":\"\",\"child_hint\":\"\",\"child_maxsize\":\"\",\"label\":\"issues\",\"mandatory\":\"false\",\"child_name\":\"issue\",\"uiTypeLabel\":\"Array.Object\",\"child_label\":\"issue\",\"child_type_label\":\"Object\",\"read_only\":\"false\",\"hint\":\"\",\"uiType\":\"array.object\",\"child_defaultValue\":\"\",\"child_type\":\"object\",\"order\":\"3\",\"max_length\":\"0\",\"child_uiUniqueId\":\"8cf8549f-a408-40ce-86c0-522fc4f6da3d\"}"}},"FlowDesigner:FD0a462ebef803051048b6688991a478b8.$type_facets":{"SimpleMapFacet":"{\"uiTypeLabel\":\"Object\",\"co_type_name\":\"FD0a462ebef803051048b6688991a478b8\",\"element_mapping_provider\":\"com.glide.flow_design.action.data.FlowDesignVariableMapper\",\"read_only\":\"false\",\"hint\":\"\",\"uiType\":\"object\",\"default_value\":\"\",\"label\":\"Body\",\"mandatory\":\"false\",\"order\":\"200\",\"max_length\":\"65000\"}"}}</serialized_content>
        <sys_class_name>sys_complex_object</sys_class_name>
        <sys_created_by>deepd</sys_created_by>
        <sys_created_on>2022-04-28 00:01:14</sys_created_on>
        <sys_domain>global</sys_domain>
        <sys_domain_path>/</sys_domain_path>
        <sys_id>ca462ebe87030510548899b73cbb35b8</sys_id>
        <sys_mod_count>4</sys_mod_count>
        <sys_name>FD0a462ebef803051048b6688991a478b8</sys_name>
        <sys_overrides/>
        <sys_package display_value="JFrog Xray Spoke" source="x_737142_jfrog_x_0">8518bb0a2f110110d2dbb6a62799b6aa</sys_package>
        <sys_policy/>
        <sys_scope display_value="JFrog Xray Spoke">8518bb0a2f110110d2dbb6a62799b6aa</sys_scope>
        <sys_update_name>sys_complex_object_ca462ebe87030510548899b73cbb35b8</sys_update_name>
        <sys_updated_by>deepd</sys_updated_by>
        <sys_updated_on>2022-05-05 18:27:59</sys_updated_on>
        <type>complex_object_schema</type>
    </sys_complex_object>
    <sys_update_version action="INSERT_OR_UPDATE">
        <action>DELETE</action>
        <application display_value="Jfrog Xray Spoke">8518bb0a2f110110d2dbb6a62799b6aa</application>
        <file_path/>
        <instance_id>667105dddb9689504d2bac44d4961987</instance_id>
        <instance_name>xrayspokestaging</instance_name>
        <name>sys_complex_object_ca462ebe87030510548899b73cbb35b8</name>
        <payload><![CDATA[<?xml version="1.0" encoding="UTF-8"?><record_update sys_domain="global" table="sys_complex_object"><sys_complex_object action="INSERT_OR_UPDATE"><label/><name>FD0a462ebef803051048b6688991a478b8</name><namespace>FlowDesigner</namespace><scope_name>8518bb0a2f110110d2dbb6a62799b6aa</scope_name><serialized_content>{"FlowDesigner:FD0a462ebef803051048b6688991a478b8":{"watch_name":"String","watch_name.$field_facets":{"SimpleMapFacet":"{\"uiTypeLabel\":\"String\",\"read_only\":\"false\",\"hint\":\"\",\"uiType\":\"string\",\"default_value\":\"\",\"label\":\"watch_name\",\"mandatory\":\"false\",\"order\":\"1\",\"max_length\":\"0\"}"},"policy_name":"String","policy_name.$field_facets":{"SimpleMapFacet":"{\"uiTypeLabel\":\"String\",\"read_only\":\"false\",\"hint\":\"\",\"uiType\":\"string\",\"default_value\":\"\",\"label\":\"policy_name\",\"mandatory\":\"false\",\"order\":\"2\",\"max_length\":\"0\"}"},"issues":[{"$60_issues":{"severity":"String","severity.$field_facets":{"SimpleMapFacet":"{\"uiTypeLabel\":\"String\",\"read_only\":\"false\",\"hint\":\"\",\"uiType\":\"string\",\"default_value\":\"\",\"label\":\"severity\",\"mandatory\":\"false\",\"order\":\"1\",\"max_length\":\"0\"}"},"summary":"String","summary.$field_facets":{"SimpleMapFacet":"{\"uiTypeLabel\":\"String\",\"read_only\":\"false\",\"hint\":\"\",\"uiType\":\"string\",\"default_value\":\"\",\"label\":\"summary\",\"mandatory\":\"false\",\"order\":\"5\",\"max_length\":\"0\"}"},"cve":"String","cve.$field_facets":{"SimpleMapFacet":"{\"uiTypeLabel\":\"String\",\"read_only\":\"false\",\"hint\":\"\",\"uiType\":\"string\",\"default_value\":\"\",\"label\":\"cve\",\"mandatory\":\"false\",\"order\":\"2\",\"max_length\":\"0\"}"},"created":"String","created.$field_facets":{"SimpleMapFacet":"{\"uiTypeLabel\":\"String\",\"read_only\":\"false\",\"hint\":\"\",\"uiType\":\"string\",\"default_value\":\"\",\"label\":\"created\",\"mandatory\":\"false\",\"order\":\"4\",\"max_length\":\"0\"}"},"type":"String","type.$field_facets":{"SimpleMapFacet":"{\"uiTypeLabel\":\"String\",\"read_only\":\"false\",\"hint\":\"\",\"uiType\":\"string\",\"default_value\":\"\",\"label\":\"type\",\"mandatory\":\"false\",\"order\":\"3\",\"max_length\":\"0\"}"}}}],"issues.$field_facets":{"SimpleMapFacet":"{\"max_rows\":null,\"default_value\":\"\",\"child_hint\":\"\",\"child_maxsize\":\"\",\"label\":\"issues\",\"mandatory\":\"false\",\"child_name\":\"issue\",\"uiTypeLabel\":\"Array.Object\",\"child_label\":\"issue\",\"child_type_label\":\"Object\",\"read_only\":\"false\",\"hint\":\"\",\"uiType\":\"array.object\",\"child_defaultValue\":\"\",\"child_type\":\"object\",\"order\":\"3\",\"max_length\":\"0\",\"child_uiUniqueId\":\"8cf8549f-a408-40ce-86c0-522fc4f6da3d\"}"}},"FlowDesigner:FD0a462ebef803051048b6688991a478b8.$type_facets":{"SimpleMapFacet":"{\"uiTypeLabel\":\"Object\",\"co_type_name\":\"FD0a462ebef803051048b6688991a478b8\",\"element_mapping_provider\":\"com.glide.flow_design.action.data.FlowDesignVariableMapper\",\"read_only\":\"false\",\"hint\":\"\",\"uiType\":\"object\",\"default_value\":\"\",\"label\":\"Body\",\"mandatory\":\"false\",\"order\":\"200\",\"max_length\":\"65000\"}"}}</serialized_content><sys_class_name>sys_complex_object</sys_class_name><sys_created_by>deepd</sys_created_by><sys_created_on>2022-04-28 00:01:14</sys_created_on><sys_domain>global</sys_domain><sys_domain_path>/</sys_domain_path><sys_id>ca462ebe87030510548899b73cbb35b8</sys_id><sys_mod_count>4</sys_mod_count><sys_name>FD0a462ebef803051048b6688991a478b8</sys_name><sys_overrides/><sys_package display_value="JFrog Xray Spoke" source="x_737142_jfrog_x_0">8518bb0a2f110110d2dbb6a62799b6aa</sys_package><sys_policy/><sys_scope display_value="JFrog Xray Spoke">8518bb0a2f110110d2dbb6a62799b6aa</sys_scope><sys_update_name>sys_complex_object_ca462ebe87030510548899b73cbb35b8</sys_update_name><sys_updated_by>deepd</sys_updated_by><sys_updated_on>2022-05-05 18:27:59</sys_updated_on><type>complex_object_schema</type></sys_complex_object></record_update>]]></payload>
        <payload_hash>1186981880</payload_hash>
        <record_name>FD0a462ebef803051048b6688991a478b8</record_name>
        <reverted_from/>
        <source>f5d4a365979b0110d872f9cfe153afff</source>
        <source_table>sys_update_set</source_table>
        <state>previous</state>
        <sys_created_by>admin</sys_created_by>
        <sys_created_on>2022-05-06 17:38:14</sys_created_on>
        <sys_id>ffe4eb65979b0110d872f9cfe153afeb</sys_id>
        <sys_mod_count>0</sys_mod_count>
        <sys_recorded_at>1809a7362cd0000001</sys_recorded_at>
        <sys_updated_by>admin</sys_updated_by>
        <sys_updated_on>2022-05-06 17:38:14</sys_updated_on>
        <type>Complex Object</type>
        <update_guid>bfe4eb65b39b011055f04d0ed3b993eb</update_guid>
        <update_guid_history>bfe4eb65b39b011055f04d0ed3b993eb:1186981880</update_guid_history>
    </sys_update_version>
    <sys_metadata_delete action="INSERT_OR_UPDATE">
        <sys_audit_delete/>
        <sys_class_name>sys_metadata_delete</sys_class_name>
        <sys_created_by>ben.ennis</sys_created_by>
        <sys_created_on>2022-05-11 17:25:27</sys_created_on>
        <sys_db_object display_value="" name="sys_complex_object">sys_complex_object</sys_db_object>
        <sys_id>0d39b62d3f0f46d1b3bb933fadccf6e1</sys_id>
        <sys_metadata>ca462ebe87030510548899b73cbb35b8</sys_metadata>
        <sys_mod_count>0</sys_mod_count>
        <sys_name>FD0a462ebef803051048b6688991a478b8</sys_name>
        <sys_package display_value="Jfrog Xray Spoke" source="x_jfrog_xray_spoke">8518bb0a2f110110d2dbb6a62799b6aa</sys_package>
        <sys_parent/>
        <sys_policy/>
        <sys_scope display_value="Jfrog Xray Spoke">8518bb0a2f110110d2dbb6a62799b6aa</sys_scope>
        <sys_scope_delete/>
        <sys_update_name>sys_complex_object_ca462ebe87030510548899b73cbb35b8</sys_update_name>
        <sys_update_version display_value="sys_complex_object_ca462ebe87030510548899b73cbb35b8">ffe4eb65979b0110d872f9cfe153afeb</sys_update_version>
        <sys_updated_by>ben.ennis</sys_updated_by>
        <sys_updated_on>2022-05-11 17:25:27</sys_updated_on>
    </sys_metadata_delete>
</record_update>
